{
  "AWSTemplateFormatVersion" : "2010-09-09",

  "Description" : "Template for installing Jenkins on Windows",

  "Parameters" : {
    

    "KeyName": {
      "Description" : "Name of an existing EC2 KeyPair to enable SSH access to the instances",
      "Type": "AWS::EC2::KeyPair::KeyName",
      "ConstraintDescription" : "must be the name of an existing EC2 KeyPair.",
      "AllowedPattern" : ".+"
    }
  },

  "Resources" : {

    "EC2Instance" : {
        "Type" : "AWS::EC2::Instance",
        "Properties" : {
            "InstanceType" : "t2.micro",
            "SecurityGroups" : [ {"Ref" : "SecurityGroup"} ],
            "KeyName" : { "Ref" : "KeyName" },
            "ImageId" : "ami-accbb6d3",
            "UserData"       : { "Fn::Base64" : { "Fn::Join" : ["", [
                
               
            ]]}}
        }
    },

    "SecurityGroup" : {
        "Type" : "AWS::EC2::SecurityGroup",
        "Properties" : {
          "GroupDescription" : "rules for opening the web and ssh ports",
          "SecurityGroupIngress" : [ {
            "IpProtocol" : "tcp",
            "FromPort" : "8080",
            "ToPort" : "8080",
            "CidrIp" : "0.0.0.0/0"
          },
          {
            "IpProtocol" : "tcp",
            "FromPort" : "22",
            "ToPort" : "22",
            "CidrIp" : "0.0.0.0/0"
          },
          {
            "IpProtocol" : "tcp",
            "FromPort" : "3389",
            "ToPort" : "3389",
            "CidrIp" : "0.0.0.0/0"
          } ]
        }
      }

  },

  "Outputs" : {
    "JenkinsURL" : {
      "Description" : "URL for Jenkins",
      "Value" : { "Fn::Join" : ["", ["http://", { "Fn::GetAtt" : [ "EC2Instance", "PublicIp" ]}, ":8080" ]] }
    }
  }
}